LICENSE
MANIFEST.in
README.md
setup.py
zisnmf/__init__.py
zisnmf/markergenes.py
zisnmf/mynmf.py
zisnmf/simulation.py
zisnmf/statsmodel.py
zisnmf/zisnmf.py
zisnmf.egg-info/PKG-INFO
zisnmf.egg-info/SOURCES.txt
zisnmf.egg-info/dependency_links.txt
zisnmf.egg-info/requires.txt
zisnmf.egg-info/top_level.txt