Metadata-Version: 2.1
Name: zisnmf
Version: 0.1.2
Summary: Zero-inflated Supervised Non-negative Matrix Factorization
Author: Feng Zeng
Author-email: zengfeng@xmu.edu.cn
Classifier: Programming Language :: Python :: 3
Classifier: License :: OSI Approved :: MIT License
Classifier: Operating System :: OS Independent
Requires-Python: >=3.6
License-File: LICENSE
Requires-Dist: matplotlib>=3.9.2
Requires-Dist: numpy>=2.0.2
Requires-Dist: pandas>=2.2.2
Requires-Dist: pyro_ppl>=1.9.1
Requires-Dist: scanpy>=1.10.3
Requires-Dist: scikit_learn>=1.5.2
Requires-Dist: scipy>=1.13.1
Requires-Dist: seaborn>=0.13.2
Requires-Dist: setuptools>=73.0.1
Requires-Dist: torch>=2.3.1
Requires-Dist: tqdm>=4.66.5
